logs/__init__.py
logs/decorators.py
logs/middleware.py
logs/registration.py
logs/settings.py
logs/models/__init__.py
logs/models/fields.py
logs/models/managers.py
django_logs-1.0.1.dist-info/LICENSE
django_logs-1.0.1.dist-info/METADATA
django_logs-1.0.1.dist-info/WHEEL
django_logs-1.0.1.dist-info/top_level.txt
django_logs-1.0.1.dist-info/RECORD
